stellar_occultations/__init__.py
stellar_occultations/stellar_occultations.py
stellar_occultations-0.1.0.dist-info/LICENSE
stellar_occultations-0.1.0.dist-info/METADATA
stellar_occultations-0.1.0.dist-info/WHEEL
stellar_occultations-0.1.0.dist-info/top_level.txt
stellar_occultations-0.1.0.dist-info/RECORD
