Metadata-Version: 2.1
Name: stellar-occultations
Version: 0.1.0
Summary: Tools to calculate diffraction patterns by stellar occultations
Home-page: https://github.com/ferwazz/stellar_occultations
Author-email: joelhcch@astro.unam.mx 
License: GNU AFFERO GENERAL PUBLIC LICENSE
Platform: UNKNOWN
Requires-Python: >=3.6
License-File: LICENSE
Requires-Dist: numpy
Requires-Dist: pandas
